<?xml version="1.0" encoding="utf-8"?>
<!-- 
# This file is part of Odoo. The COPYRIGHT file at the top level of
# this module contains the full copyright and licensing details.
-->
<odoo>
  <data>

    <record id="import_datev_action" model="ir.actions.act_window">
      <field name="name">DATEV Import</field>
      <field name="type">ir.actions.act_window</field>
      <field name="res_model">import.datev</field>
      <!--<field name="view_type">form</field>-->
      <field name="view_id" ref="import_datev_tree_view"/>
    </record>
    <menuitem action="import_datev_action" id="datev_import_menu" parent="ecoservice_financeinterface.menu_finance_interface" sequence="20" groups="ecoservice_financeinterface.group_ecofi_financeinterface"/>

  </data>
</odoo>
